.coveragerc
LICENSE.txt
MANIFEST.in
README.md
pytest.ini
requirements.txt
setup.py
tests/__init__.py
tests/conftest.py
tests/test_torch_vs_numpy.py
torch_crystals/__init__.py
torch_crystals/__version.py
torch_crystals/intensity_maps.py
torch_crystals/utils.py
torch_crystals.egg-info/PKG-INFO
torch_crystals.egg-info/SOURCES.txt
torch_crystals.egg-info/dependency_links.txt
torch_crystals.egg-info/requires.txt
torch_crystals.egg-info/top_level.txt
torch_crystals/numpy_simulations/__init__.py
torch_crystals/simulations/__init__.py
torch_crystals/simulations/atom_factor.py
torch_crystals/simulations/intensities.py
torch_crystals/simulations/lattice.py
torch_crystals/simulations/miller_indices.py
torch_crystals/simulations/rotations.py
torch_crystals/simulations/torch_crystal.py